{
  "buildFiles": [
    "C:\\Users\\aman\\Desktop\\New folder\\flutter\\packages\\flutter_tools\\gradle\\src\\main\\groovy\\CMakeLists.txt"
  ],
  "cleanCommandsComponents": [
    [
      "C:\\Users\\aman\\Desktop\\commandlinetools-win-11076708_latest\\cmdline-tools\\cmake\\3.22.1\\bin\\ninja.exe",
      "-C",
      "C:\\Users\\aman\\Desktop\\restaurant\\android\\app\\.cxx\\Debug\\1xa4s332\\x86_64",
      "clean"
    ]
  ],
  "buildTargetsCommandComponents": [
    "C:\\Users\\aman\\Desktop\\commandlinetools-win-11076708_latest\\cmdline-tools\\cmake\\3.22.1\\bin\\ninja.exe",
    "-C",
    "C:\\Users\\aman\\Desktop\\restaurant\\android\\app\\.cxx\\Debug\\1xa4s332\\x86_64",
    "{LIST_OF_TARGETS_TO_BUILD}"
  ],
  "libraries": {},
  "toolchains": {
    "toolchain": {
      "cCompilerExecutable": "C:\\Users\\aman\\Desktop\\commandlinetools-win-11076708_latest\\cmdline-tools\\ndk\\26.3.11579264\\toolchains\\llvm\\prebuilt\\windows-x86_64\\bin\\clang.exe",
      "cppCompilerExecutable": "C:\\Users\\aman\\Desktop\\commandlinetools-win-11076708_latest\\cmdline-tools\\ndk\\26.3.11579264\\toolchains\\llvm\\prebuilt\\windows-x86_64\\bin\\clang++.exe"
    }
  },
  "cFileExtensions": [],
  "cppFileExtensions": []
}